connectrpc/__init__.py
connectrpc/_asyncio_timeout.py
connectrpc/_client_async.py
connectrpc/_client_shared.py
connectrpc/_client_sync.py
connectrpc/_codec.py
connectrpc/_compression.py
connectrpc/_envelope.py
connectrpc/_gen/status_pb2.py
connectrpc/_gen/status_pb2.pyi
connectrpc/_headers.py
connectrpc/_interceptor_async.py
connectrpc/_interceptor_sync.py
connectrpc/_protocol.py
connectrpc/_protocol_connect.py
connectrpc/_protocol_grpc.py
connectrpc/_protocol_server.py
connectrpc/_response_metadata.py
connectrpc/_server_async.py
connectrpc/_server_shared.py
connectrpc/_server_sync.py
connectrpc/_version.py
connectrpc/client.py
connectrpc/code.py
connectrpc/errors.py
connectrpc/interceptor.py
connectrpc/method.py
connectrpc/py.typed
connectrpc/request.py
connectrpc/server.py
connect_python-0.7.1.dist-info/licenses/LICENSE
connect_python-0.7.1.dist-info/WHEEL
connect_python-0.7.1.dist-info/METADATA
connect_python-0.7.1.dist-info/RECORD
