Metadata-Version: 2.4
Name: connect-python
Version: 0.7.1
Summary: Server and client runtime library for Connect RPC
Keywords: rpc,grpc,connect,protobuf,http
License-File: LICENSE
Classifier: Development Status :: 3 - Alpha
Classifier: Intended Audience :: Developers
Classifier: License :: OSI Approved :: Apache Software License
Classifier: Operating System :: OS Independent
Classifier: Programming Language :: Python :: 3
Classifier: Programming Language :: Python :: 3.10
Classifier: Programming Language :: Python :: 3.11
Classifier: Programming Language :: Python :: 3.12
Classifier: Programming Language :: Python :: 3.13
Classifier: Programming Language :: Python :: 3.14
Classifier: Topic :: Internet :: WWW/HTTP
Classifier: Topic :: Software Development :: Libraries :: Python Modules
Classifier: Typing :: Typed
Requires-Dist: httpx>=0.28.1
Requires-Dist: protobuf>=5.28
Maintainer: Anuraag Agrawal, Spencer Nelson, Stefan VanBuren, Yasushi Itoh
Maintainer-email: Anuraag Agrawal <anuraaga@gmail.com>, Spencer Nelson <spencer@firetiger.com>, Stefan VanBuren <svanburen@buf.build>, Yasushi Itoh <i2y.may.roku@gmail.com>
Requires-Python: >=3.10
Project-URL: Homepage, https://github.com/connectrpc/connect-python
Project-URL: Issues, https://github.com/connectrpc/connect-python/issues
Project-URL: Repository, https://github.com/connectrpc/connect-python
